dashboardUtility/Dashboard_Creation.py
dashboardUtility/Dashboard_Definition.py
dashboardUtility/Dashbrd_dgn.py
dashboardUtility/FreeHand_SQL_Model.py
dashboardUtility/FreeHand_Visual_Model.py
dashboardUtility/Generate_Visual.py
dashboardUtility/SQL_Model.py
dashboardUtility/Source_SQL.py
dashboardUtility/Visual_Model.py
dashboardUtility/__init__.py
dashboardUtility-0.0.2.dist-info/LICENCE.txt
dashboardUtility-0.0.2.dist-info/METADATA
dashboardUtility-0.0.2.dist-info/WHEEL
dashboardUtility-0.0.2.dist-info/top_level.txt
dashboardUtility-0.0.2.dist-info/RECORD
